checkv/__init__.py
checkv/cli.py
checkv/utility.py
checkv/modules/__init__.py
checkv/modules/complete_genomes.py
checkv/modules/completeness.py
checkv/modules/contamination.py
checkv/modules/download_database.py
checkv/modules/end_to_end.py
checkv/modules/quality_summary.py
checkv/modules/update_database.py
checkv-1.0.3.dist-info/entry_points.txt
checkv-1.0.3.dist-info/LICENSE.txt
checkv-1.0.3.dist-info/WHEEL
checkv-1.0.3.dist-info/METADATA
checkv-1.0.3.dist-info/RECORD
