Metadata-Version: 2.1
Name: checkv
Version: 1.0.3
Summary: CheckV: Assessing the quality of metagenome-assembled viral genomes
Author-email: Stephen Nayfach <snayfach@lbl.gov>, Antonio Camargo <antoniop.camargo@lbl.gov>, Simon Roux <sroux@lbl.gov>
Requires-Python: >=3.6
Classifier: Intended Audience :: Science/Research
Classifier: Natural Language :: English
Classifier: Topic :: Software Development :: Libraries
Classifier: Topic :: Scientific/Engineering :: Bio-Informatics
Classifier: License :: OSI Approved :: BSD License
Classifier: Programming Language :: Python :: 3
Requires-Dist: biopython
Requires-Dist: kcounter
Requires-Dist: numpy>=1.5
Requires-Dist: psutil
Requires-Dist: requests
Project-URL: Home, https://bitbucket.org/berkeleylab/checkv/
Project-URL: Source, https://bitbucket.org/berkeleylab/checkv/
